codons.py
dnds.py
dnds-2.1.dist-info/METADATA
dnds-2.1.dist-info/RECORD
dnds-2.1.dist-info/WHEEL
dnds-2.1.dist-info/top_level.txt
